{
    "name": "sap.watt.common.compare.service.Compare",
    "description": "The Compare service interface",
    "extends": [
        "sap.watt.common.service.editor.Editor",
        "sap.watt.common.service.editor.UndoRedo"
    ],
    "methods": {
        "compare": {
            "params": [
                {
                    "name": "oDocument",
                    "type": "object"
                },
                {
                    "name": "sRightSide",
                    "type": "string",
                    "description": "The content to compare with"
                },
                {
                    "name": "sLeftSide",
                    "type": "string",
                    "optional": true,
                    "description": "In case you don't want to compare with the document content you can provide content to the left side instead"
                },
                {
                 	"name": "bReadOnly",
                    "type": "boolean",
                    "optional": true,
                    "default" : "false", 
                    "description": "opens the compare tab in read only mode"
                }
            ],
            "description": "The method opens the compare editor as a new tab"
        }
    }
}